rfc_kits/__init__.py
rfc_kits/attribute.py
rfc_kits/bcp_download.py
rfc_kits/rfc_download.py
rfc_kits/rfc_editor.py
rfc_kits-0.2.0.dist-info/LICENSE
rfc_kits-0.2.0.dist-info/METADATA
rfc_kits-0.2.0.dist-info/WHEEL
rfc_kits-0.2.0.dist-info/entry_points.txt
rfc_kits-0.2.0.dist-info/top_level.txt
rfc_kits-0.2.0.dist-info/zip-safe
rfc_kits-0.2.0.dist-info/RECORD
